delo/AbstractDE.py
delo/CustomExceptions.py
delo/DElo.py
delo/DElo_ties.py
delo/DElo_ties_and_QI.py
delo/DescribedFunction.py
delo/DistributionUtilities.py
delo/Logger.py
delo/PickleLogger.py
delo/QualityOfImprovement.py
delo/SHADE.py
delo/__init__.py
delo/example.py
delo-0.9.0.dist-info/LICENSE
delo-0.9.0.dist-info/METADATA
delo-0.9.0.dist-info/WHEEL
delo-0.9.0.dist-info/top_level.txt
delo-0.9.0.dist-info/RECORD
