Metadata-Version: 2.1
Name: delo
Version: 0.9.0
Summary: Differential Evolution with Elo-based adaptation
Home-page: https://github.com/mrdomani/delo
Author: Przemysław Adam Chojecki, Paweł Morgen, Michał Okulewicz
Author-email: seriousmorgen@protonmail.com
License: UNKNOWN
Project-URL: Bug Tracker, https://github.com/mrdomani/delo/issues
Platform: UNKNOWN
Classifier: Programming Language :: Python :: 3
Classifier: License :: OSI Approved :: MIT License
Classifier: Operating System :: OS Independent
Classifier: Topic :: Scientific/Engineering :: Mathematics
Requires-Python: >=3.6
License-File: LICENSE
Requires-Dist: numpy
Requires-Dist: scipy
